loggui/__init__.py
loggui/__main__.py
loggui/handler.py
loggui/widgets/__init__.py
loggui/widgets/record_view.py
loggui/widgets/settings.py
loggui-0.2.5.dist-info/METADATA
loggui-0.2.5.dist-info/RECORD
loggui-0.2.5.dist-info/WHEEL
loggui-0.2.5.dist-info/top_level.txt
