Metadata-Version: 2.1
Name: loggui
Version: 0.2.5
Summary: GUI handler for python logging
Home-page: https://gitlab.com/octonezd/loggui
Author: OctoNezd
Author-email: nezd@protonmail.com
License: UNKNOWN
Platform: UNKNOWN
Classifier: Programming Language :: Python :: 3.5
Classifier: License :: OSI Approved :: MIT License
Classifier: Operating System :: OS Independent
Classifier: Programming Language :: Python :: 3 :: Only
Requires-Dist: pyside2
